htk/__init__.py
htk/__version__.py
htk/settings.py
htk/encoders/__init__.py
htk/utils/__init__.py
htk/utils/debuggers.py
htk/utils/http.py
htk/utils/slack.py
htk/utils/validate_emails_csv.py
tests/utils/__init__.py
tests/utils/conftest.py
tests/utils/test_slack.py
htk-2.1.0.dist-info/LICENSE
htk-2.1.0.dist-info/LICENSE.md
htk-2.1.0.dist-info/METADATA
htk-2.1.0.dist-info/WHEEL
htk-2.1.0.dist-info/top_level.txt
htk-2.1.0.dist-info/RECORD
