Metadata-Version: 2.1
Name: htk
Version: 2.1.0
Summary: A set of convenience utils for Python
Home-page: https://github.com/hacktoolkit/python-htk
Author: Hacktoolkit
Author-email: hello@hacktoolkit.com
License: MIT
Project-URL: Documentation, https://github.com/hacktoolkit/python-htk
Project-URL: Source, https://github.com/hacktoolkit/python-htk
Keywords: python debugging slack requests apis
Classifier: Development Status :: 5 - Production/Stable
Classifier: Intended Audience :: Developers
Classifier: Topic :: Text Processing :: General
Classifier: License :: OSI Approved :: MIT License
Classifier: Programming Language :: Python :: 3
License-File: LICENSE
License-File: LICENSE.md
Requires-Dist: python-dotenv (>=0.13.0)
Requires-Dist: requests (>=2)
Provides-Extra: dev
Provides-Extra: test
Requires-Dist: pytest ; extra == 'test'
Requires-Dist: pytest-cov ; extra == 'test'
